doorstopqt/__init__.py
doorstopqt/attributeview.py
doorstopqt/categoryselector.py
doorstopqt/createcatdiag.py
doorstopqt/documentview.py
doorstopqt/icon.py
doorstopqt/linkview.py
doorstopqt/mainview.py
doorstopqt/markdownview.py
doorstopqt/version.py
doorstopqt-0.1.1.dist-info/METADATA
doorstopqt-0.1.1.dist-info/WHEEL
doorstopqt-0.1.1.dist-info/entry_points.txt
doorstopqt-0.1.1.dist-info/top_level.txt
doorstopqt-0.1.1.dist-info/RECORD
