Metadata-Version: 2.1
Name: doorstopqt
Version: 0.1.1
Summary: UNKNOWN
Home-page: UNKNOWN
Author: Johnny Oskarsson
Author-email: johnny@joskar.se
License: UNKNOWN
Platform: UNKNOWN
Requires-Dist: doorstop (<2,>=1.4)
Requires-Dist: pyqt5 (<6,>=5.9)
Requires-Dist: markdown (<3,>=2.6.9)
